{
    "testId": 45959,
    "orderId": 45958,
    "patientId": 45677,
    "resultDate": "2001-01-15",
    "testResults": [
        {
            "componentName": "White Blood Cell Count",
            "componentRefHi": 11.0,
            "componentRefLo": 4.0,
            "componentUnits": "10^9/L",
            "resultValue": 11.610000497683973
        },
        {
            "componentName": "Hemoglobin",
            "componentRefHi": 17.5,
            "componentRefLo": 13.0,
            "componentUnits": "g/dL",
            "resultValue": 11.580298457631315
        },
        {
            "componentName": "Platelet Count",
            "componentRefHi": 450,
            "componentRefLo": 150,
            "componentUnits": "10^9/L",
            "resultValue": 301.34266479214114
        }
    ]
}