{
    "testId": 39485,
    "orderId": 39484,
    "patientId": 38180,
    "resultDate": "2006-08-13",
    "testResults": [
        {
            "componentName": "Glucose",
            "componentRefHi": 140,
            "componentRefLo": 70,
            "componentUnits": "mg/dL",
            "resultValue": 74.6198844848045
        },
        {
            "componentName": "Creatinine",
            "componentRefHi": 1.3,
            "componentRefLo": 0.6,
            "componentUnits": "mg/dL",
            "resultValue": 0.5865339236179744
        },
        {
            "componentName": "Potassium",
            "componentRefHi": 5.1,
            "componentRefLo": 3.5,
            "componentUnits": "mmol/L",
            "resultValue": 5.386591861585824
        }
    ]
}