{
    "testId": 27480,
    "orderId": 27479,
    "patientId": 26765,
    "resultDate": "1985-02-26",
    "testResults": [
        {
            "componentName": "White Blood Cell Count",
            "componentRefHi": 11.0,
            "componentRefLo": 4.0,
            "componentUnits": "10^9/L",
            "resultValue": 8.070350698411435
        },
        {
            "componentName": "Hemoglobin",
            "componentRefHi": 17.5,
            "componentRefLo": 13.0,
            "componentUnits": "g/dL",
            "resultValue": 19.947789093263047
        },
        {
            "componentName": "Platelet Count",
            "componentRefHi": 450,
            "componentRefLo": 150,
            "componentUnits": "10^9/L",
            "resultValue": 705.1087448686415
        }
    ]
}