{
    "testId": 44881,
    "orderId": 44880,
    "patientId": 44658,
    "resultDate": "2014-07-05",
    "testResults": [
        {
            "componentName": "Thyroid Stimulating Hormone (TSH)",
            "componentRefHi": 4.5,
            "componentRefLo": 0.4,
            "componentUnits": "mIU/L",
            "resultValue": 4.7357437189007126
        },
        {
            "componentName": "Free T4",
            "componentRefHi": 1.8,
            "componentRefLo": 0.8,
            "componentUnits": "ng/dL",
            "resultValue": 0.9168509064938926
        }
    ]
}