{
    "testId": 26364,
    "orderId": 26363,
    "patientId": 24313,
    "resultDate": "1999-07-05",
    "testResults": [
        {
            "componentName": "White Blood Cell Count",
            "componentRefHi": 11.0,
            "componentRefLo": 4.0,
            "componentUnits": "10^9/L",
            "resultValue": 4.774215067808228
        },
        {
            "componentName": "Hemoglobin",
            "componentRefHi": 17.5,
            "componentRefLo": 13.0,
            "componentUnits": "g/dL",
            "resultValue": 12.731408560282388
        },
        {
            "componentName": "Platelet Count",
            "componentRefHi": 450,
            "componentRefLo": 150,
            "componentUnits": "10^9/L",
            "resultValue": 272.7945174892365
        }
    ]
}