{
    "testId": 47305,
    "orderId": 47304,
    "patientId": 46421,
    "resultDate": "1996-10-11",
    "testResults": [
        {
            "componentName": "Forced Expiratory Volume (FEV1)",
            "componentRefHi": 3.5,
            "componentRefLo": 2.0,
            "componentUnits": "L",
            "resultValue": 2.9419835677640465
        },
        {
            "componentName": "Peak Expiratory Flow (PEF)",
            "componentRefHi": 9.0,
            "componentRefLo": 5.0,
            "componentUnits": "L/s",
            "resultValue": 8.036490366906241
        }
    ]
}