{
    "testId": 34046,
    "orderId": 34045,
    "patientId": 33926,
    "resultDate": "2017-07-28",
    "testResults": [
        {
            "componentName": "Forced Expiratory Volume (FEV1)",
            "componentRefHi": 3.5,
            "componentRefLo": 2.0,
            "componentUnits": "L",
            "resultValue": 2.68283754149938
        },
        {
            "componentName": "Peak Expiratory Flow (PEF)",
            "componentRefHi": 9.0,
            "componentRefLo": 5.0,
            "componentUnits": "L/s",
            "resultValue": 6.395758092642185
        }
    ]
}