{
    "testId": 41692,
    "orderId": 41691,
    "patientId": 40842,
    "resultDate": "2011-10-19",
    "testResults": [
        {
            "componentName": "Forced Expiratory Volume (FEV1)",
            "componentRefHi": 3.5,
            "componentRefLo": 2.0,
            "componentUnits": "L",
            "resultValue": 1.9937644116430584
        },
        {
            "componentName": "Peak Expiratory Flow (PEF)",
            "componentRefHi": 9.0,
            "componentRefLo": 5.0,
            "componentUnits": "L/s",
            "resultValue": 2.291268236427296
        }
    ]
}