{
    "testId": 21014,
    "orderId": 21013,
    "patientId": 20614,
    "resultDate": "1962-10-15",
    "testResults": [
        {
            "componentName": "Glucose",
            "componentRefHi": 140,
            "componentRefLo": 70,
            "componentUnits": "mg/dL",
            "resultValue": 133.59968268879192
        },
        {
            "componentName": "Creatinine",
            "componentRefHi": 1.3,
            "componentRefLo": 0.6,
            "componentUnits": "mg/dL",
            "resultValue": 1.3294767887661527
        },
        {
            "componentName": "Potassium",
            "componentRefHi": 5.1,
            "componentRefLo": 3.5,
            "componentUnits": "mmol/L",
            "resultValue": 4.222503887837058
        }
    ]
}