{
    "testId": 45961,
    "orderId": 45960,
    "patientId": 45677,
    "resultDate": "2001-01-18",
    "testResults": [
        {
            "componentName": "White Blood Cell Count",
            "componentRefHi": 11.0,
            "componentRefLo": 4.0,
            "componentUnits": "10^9/L",
            "resultValue": 7.194782609224836
        },
        {
            "componentName": "Hemoglobin",
            "componentRefHi": 17.5,
            "componentRefLo": 13.0,
            "componentUnits": "g/dL",
            "resultValue": 18.98680033499747
        },
        {
            "componentName": "Platelet Count",
            "componentRefHi": 450,
            "componentRefLo": 150,
            "componentUnits": "10^9/L",
            "resultValue": 331.4419259428383
        }
    ]
}