{
    "testId": 11808,
    "orderId": 11807,
    "patientId": 11728,
    "resultDate": "2015-12-16",
    "testResults": [
        {
            "componentName": "Total Cholesterol",
            "componentRefHi": 200,
            "componentRefLo": 100,
            "componentUnits": "mg/dL",
            "resultValue": 189.74686967471047
        },
        {
            "componentName": "LDL Cholesterol",
            "componentRefHi": 130,
            "componentRefLo": 50,
            "componentUnits": "mg/dL",
            "resultValue": 129.87423926562946
        },
        {
            "componentName": "HDL Cholesterol",
            "componentRefHi": 60,
            "componentRefLo": 40,
            "componentUnits": "mg/dL",
            "resultValue": 55.161557910787536
        }
    ]
}