{
    "testId": 47237,
    "orderId": 47236,
    "patientId": 46421,
    "resultDate": "1993-09-21",
    "testResults": [
        {
            "componentName": "Forced Expiratory Volume (FEV1)",
            "componentRefHi": 3.5,
            "componentRefLo": 2.0,
            "componentUnits": "L",
            "resultValue": 1.036118170193609
        },
        {
            "componentName": "Peak Expiratory Flow (PEF)",
            "componentRefHi": 9.0,
            "componentRefLo": 5.0,
            "componentUnits": "L/s",
            "resultValue": 8.721165166285058
        }
    ]
}