{
    "testId": 40439,
    "orderId": 40438,
    "patientId": 39997,
    "resultDate": "1993-10-28",
    "testResults": [
        {
            "componentName": "Total Cholesterol",
            "componentRefHi": 200,
            "componentRefLo": 100,
            "componentUnits": "mg/dL",
            "resultValue": 149.54259950718313
        },
        {
            "componentName": "LDL Cholesterol",
            "componentRefHi": 130,
            "componentRefLo": 50,
            "componentUnits": "mg/dL",
            "resultValue": 102.10504513837428
        },
        {
            "componentName": "HDL Cholesterol",
            "componentRefHi": 60,
            "componentRefLo": 40,
            "componentUnits": "mg/dL",
            "resultValue": 23.35697748453621
        }
    ]
}