{
    "testId": 29296,
    "orderId": 29295,
    "patientId": 28862,
    "resultDate": "1987-06-14",
    "testResults": [
        {
            "componentName": "Total Cholesterol",
            "componentRefHi": 200,
            "componentRefLo": 100,
            "componentUnits": "mg/dL",
            "resultValue": 179.79956358842622
        },
        {
            "componentName": "LDL Cholesterol",
            "componentRefHi": 130,
            "componentRefLo": 50,
            "componentUnits": "mg/dL",
            "resultValue": 169.24566221461757
        },
        {
            "componentName": "HDL Cholesterol",
            "componentRefHi": 60,
            "componentRefLo": 40,
            "componentUnits": "mg/dL",
            "resultValue": 38.793977094150165
        }
    ]
}