{
    "testId": 40595,
    "orderId": 40594,
    "patientId": 39997,
    "resultDate": "2009-04-12",
    "testResults": [
        {
            "componentName": "Total Cholesterol",
            "componentRefHi": 200,
            "componentRefLo": 100,
            "componentUnits": "mg/dL",
            "resultValue": 116.09570015544193
        },
        {
            "componentName": "LDL Cholesterol",
            "componentRefHi": 130,
            "componentRefLo": 50,
            "componentUnits": "mg/dL",
            "resultValue": 147.5544416758213
        },
        {
            "componentName": "HDL Cholesterol",
            "componentRefHi": 60,
            "componentRefLo": 40,
            "componentUnits": "mg/dL",
            "resultValue": 52.70653905413729
        }
    ]
}