{
    "testId": 24234,
    "orderId": 24233,
    "patientId": 24106,
    "resultDate": "2022-11-21",
    "testResults": [
        {
            "componentName": "Glucose",
            "componentRefHi": 140,
            "componentRefLo": 70,
            "componentUnits": "mg/dL",
            "resultValue": 131.7027583597323
        },
        {
            "componentName": "Creatinine",
            "componentRefHi": 1.3,
            "componentRefLo": 0.6,
            "componentUnits": "mg/dL",
            "resultValue": 0.9746199654754291
        },
        {
            "componentName": "Potassium",
            "componentRefHi": 5.1,
            "componentRefLo": 3.5,
            "componentUnits": "mmol/L",
            "resultValue": 4.057851576614872
        }
    ]
}