{
    "testId": 46261,
    "orderId": 46260,
    "patientId": 45677,
    "resultDate": "2016-05-04",
    "testResults": [
        {
            "componentName": "White Blood Cell Count",
            "componentRefHi": 11.0,
            "componentRefLo": 4.0,
            "componentUnits": "10^9/L",
            "resultValue": 8.532897745804659
        },
        {
            "componentName": "Hemoglobin",
            "componentRefHi": 17.5,
            "componentRefLo": 13.0,
            "componentUnits": "g/dL",
            "resultValue": 13.414503421289659
        },
        {
            "componentName": "Platelet Count",
            "componentRefHi": 450,
            "componentRefLo": 150,
            "componentUnits": "10^9/L",
            "resultValue": 254.0755461191757
        }
    ]
}