{
    "testId": 41655,
    "orderId": 41654,
    "patientId": 40842,
    "resultDate": "2010-03-11",
    "testResults": [
        {
            "componentName": "Forced Expiratory Volume (FEV1)",
            "componentRefHi": 3.5,
            "componentRefLo": 2.0,
            "componentUnits": "L",
            "resultValue": 1.2056966319691322
        },
        {
            "componentName": "Peak Expiratory Flow (PEF)",
            "componentRefHi": 9.0,
            "componentRefLo": 5.0,
            "componentUnits": "L/s",
            "resultValue": 5.757776905781415
        }
    ]
}